nose_reportportal/__init__.py
nose_reportportal/plugin.py
nose_reportportal/service.py
nose_reportportal-1.0.0.dist-info/LICENSE
nose_reportportal-1.0.0.dist-info/METADATA
nose_reportportal-1.0.0.dist-info/WHEEL
nose_reportportal-1.0.0.dist-info/entry_points.txt
nose_reportportal-1.0.0.dist-info/top_level.txt
nose_reportportal-1.0.0.dist-info/RECORD
