Metadata-Version: 2.1
Name: nose-reportportal
Version: 1.0.0
Summary: Agent for Reporting results of tests to the Report Portal
Home-page: https://github.com/reportportal/agent-python-nosetests
Author: Dzmitry Kolb
Author-email: dm.kolb@gmail.com
License: Apache 2.0
Download-URL: https://github.com/reportportal/agent-python-nosetests
Keywords: testing,reporting,reportportal,nose
Platform: UNKNOWN
Classifier: Programming Language :: Python :: 2.7
Classifier: Programming Language :: Python :: 3.4
Classifier: Programming Language :: Python :: 3.5
Classifier: Programming Language :: Python :: 3.6
Requires-Dist: reportportal-client (~=5.0)
Requires-Dist: nose (>=1.3.0)
